{
    "revert": false,
    "generation": 9,
    "testcase": {
        "field": "[\"spec\", \"rabbitmq\", \"additionalPlugins\", 0]",
        "testcase": "string-change"
    },
    "feature_gate": 51,
    "crash_result": "Pass",
    "input_result": {
        "responsible_field": null
    },
    "health_result": "Pass",
    "state_result": {
        "oracle": "SystemState",
        "message": "Found no matching fields for input",
        "input_delta": {
            "prev": "NotPresent",
            "curr": "TPp\u00fb\u00db\u00e8\u00dc94Z\u00f9d\u00ebY\u00d3Q\u00e2l\u00c5es\u00d8\u00cf\u00e2\u00ee\u00fd6d\u00f1g\u00c7h\u00e9",
            "path": [
                "spec",
                "rabbitmq",
                "additionalPlugins",
                0
            ]
        },
        "matched_system_delta": null
    },
    "log_result": "Pass",
    "custom_result": null,
    "misc_result": null,
    "recovery_result": null
}