{
      "trial_num": "03-0009",
      "duration": "00:15:32",
      "num_tests": 3,
      "error": {
            "revert": false,
            "generation": 1,
            "testcase": {
                  "field": "[\"spec\", \"tidb\", \"dnsConfig\"]",
                  "testcase": "object-deletion"
            },
            "feature_gate": 51,
            "crash_result": "Pass",
            "input_result": "Pass",
            "health_result": {
                  "oracle": "SystemHealth",
                  "message": "statefulset: test-cluster-tidb replicas [3] ready_replicas [2]\ncr: CR status unhealthy condition [Ready] status [False] message [Statefulset(s) are in progress]\n"
            },
            "state_result": "Pass",
            "log_result": {
                  "responsible_field": [
                        "spec",
                        "tidb",
                        "dnsConfig",
                        "options",
                        0,
                        "name"
                  ]
            },
            "custom_result": null,
            "misc_result": null,
            "recovery_result": "Pass"
      }
}